<?xml version="1.0" encoding="UTF-8"?>
<!DOCTYPE GranuleMetaDataFile SYSTEM "http://ecsinfo.gsfc.nasa.gov/ECSInfo/ecsmetadata/dtds/DPL/ECS/ScienceGranuleMetadata.dtd">
<GranuleMetaDataFile>
    <DTDVersion>1.0</DTDVersion>
    <DataCenterId>EDC</DataCenterId>
    <GranuleURMetaData>
        <GranuleUR>SC:MYD11A1.006:2428328540</GranuleUR>
        <DbID>2428328540</DbID>
        <InsertTime>2021-01-02 12:25:18.184</InsertTime>
        <LastUpdate>2021-01-02 12:25:18.184</LastUpdate>
        <CollectionMetaData>
            <ShortName>MYD11A1</ShortName>
            <VersionID>6</VersionID>
        </CollectionMetaData>
        <DataFiles>
            <DataFileContainer>
                <DistributedFileName>MYD11A1.A2021001.h27v07.006.2021002181929.hdf</DistributedFileName>
                <FileSize>3450862</FileSize>
                <ChecksumType>CKSUM</ChecksumType>
                <Checksum>980892363</Checksum>
                <ChecksumOrigin>DPLIngst</ChecksumOrigin>
            </DataFileContainer>
        </DataFiles>
        <ECSDataGranule>
            <SizeMBECSDataGranule>3.291</SizeMBECSDataGranule>
            <ReprocessingPlanned>further update is anticipated</ReprocessingPlanned>
            <ReprocessingActual>reprocessed</ReprocessingActual>
            <LocalGranuleID>MYD11A1.A2021001.h27v07.006.2021002181929.hdf</LocalGranuleID>
            <DayNightFlag>Both</DayNightFlag>
            <ProductionDateTime>2021-01-02 18:19:29.000</ProductionDateTime>
            <LocalVersionID>6.4.4AS</LocalVersionID>
        </ECSDataGranule>
        <PGEVersionClass>
            <PGEVersion>6.4.22</PGEVersion>
        </PGEVersionClass>
        <RangeDateTime>
            <RangeEndingTime>23:59:59.000000</RangeEndingTime>
            <RangeEndingDate>2021-01-01</RangeEndingDate>
            <RangeBeginningTime>00:00:00.000000</RangeBeginningTime>
            <RangeBeginningDate>2021-01-01</RangeBeginningDate>
        </RangeDateTime>
        <SpatialDomainContainer>
            <HorizontalSpatialDomainContainer>
                <GPolygon>
                    <Boundary>
                        <Point>
                            <PointLongitude>95.7715552591434</PointLongitude>
                            <PointLatitude>19.9958333333333</PointLatitude>
                        </Point>
                        <Point>
                            <PointLongitude>106.413314759931</PointLongitude>
                            <PointLatitude>19.9958333333333</PointLatitude>
                        </Point>
                        <Point>
                            <PointLongitude>101.541031745138</PointLongitude>
                            <PointLatitude>10.0041666666667</PointLatitude>
                        </Point>
                        <Point>
                            <PointLongitude>91.3865217197192</PointLongitude>
                            <PointLatitude>10.0041666666667</PointLatitude>
                        </Point>
                    </Boundary>
                </GPolygon>
            </HorizontalSpatialDomainContainer>
        </SpatialDomainContainer>
        <MeasuredParameter>
            <MeasuredParameterContainer>
                <ParameterName>MOD 1KM L3 LST</ParameterName>
                <QAStats>
                    <QAPercentMissingData>0</QAPercentMissingData>
                    <QAPercentOutofBoundsData>0</QAPercentOutofBoundsData>
                    <QAPercentInterpolatedData>0</QAPercentInterpolatedData>
                    <QAPercentCloudCover>25</QAPercentCloudCover>
                </QAStats>
                <QAFlags>
                    <AutomaticQualityFlag>Passed</AutomaticQualityFlag>
                    <AutomaticQualityFlagExplanation>No automatic quality assessment is performed in the PGE.</AutomaticQualityFlagExplanation>
                    <OperationalQualityFlag>Passed</OperationalQualityFlag>
                    <OperationalQualityFlagExplanation>Passed</OperationalQualityFlagExplanation>
                    <ScienceQualityFlag>Not Investigated</ScienceQualityFlag>
                    <ScienceQualityFlagExplanation>See http://landweb.nascom.nasa.gov/cgi-bin/QA_WWW/qaFlagPage.cgi?sat=aqua for the product Science Quality status.</ScienceQualityFlagExplanation>
                </QAFlags>
            </MeasuredParameterContainer>
        </MeasuredParameter>
        <Platform>
            <PlatformShortName>Aqua</PlatformShortName>
            <Instrument>
                <InstrumentShortName>MODIS</InstrumentShortName>
                <Sensor>
                    <SensorShortName>MODIS</SensorShortName>
                </Sensor>
            </Instrument>
        </Platform>
        <PSAs>
            <PSA>
                <PSAName>QAPERCENTGOODQUALITY</PSAName>
                <PSAValue>23</PSAValue>
            </PSA>
            <PSA>
                <PSAName>QAPERCENTOTHERQUALITY</PSAName>
                <PSAValue>10</PSAValue>
            </PSA>
            <PSA>
                <PSAName>QAPERCENTNOTPRODUCEDCLOUD</PSAName>
                <PSAValue>25</PSAValue>
            </PSA>
            <PSA>
                <PSAName>QAPERCENTNOTPRODUCEDOTHER</PSAName>
                <PSAValue>42</PSAValue>
            </PSA>
            <PSA>
                <PSAName>N_GRAN_POINTERS</PSAName>
                <PSAValue>18</PSAValue>
            </PSA>
            <PSA>
                <PSAName>HORIZONTALTILENUMBER</PSAName>
                <PSAValue>27</PSAValue>
            </PSA>
            <PSA>
                <PSAName>VERTICALTILENUMBER</PSAName>
                <PSAValue>07</PSAValue>
            </PSA>
            <PSA>
                <PSAName>TileID</PSAName>
                <PSAValue>51027007</PSAValue>
            </PSA>
            <PSA>
                <PSAName>QAFRACTIONGOODQUALITY</PSAName>
                <PSAValue>0.2294910</PSAValue>
            </PSA>
            <PSA>
                <PSAName>QAFRACTIONOTHERQUALITY</PSAName>
                <PSAValue>0.1003153</PSAValue>
            </PSA>
            <PSA>
                <PSAName>QAFRACTIONNOTPRODUCEDCLOUD</PSAName>
                <PSAValue>0.2460368</PSAValue>
            </PSA>
            <PSA>
                <PSAName>QAFRACTIONNOTPRODUCEDOTHER</PSAName>
                <PSAValue>0.4241569</PSAValue>
            </PSA>
            <PSA>
                <PSAName>CLOUD_CONTAMINATED_LST_SCREENED</PSAName>
                <PSAValue>YES</PSAValue>
            </PSA>
            <PSA>
                <PSAName>identifier_product_doi</PSAName>
                <PSAValue>10.5067/MODIS/MYD11A1.006</PSAValue>
            </PSA>
            <PSA>
                <PSAName>identifier_product_doi_authority</PSAName>
                <PSAValue>http://dx.doi.org</PSAValue>
            </PSA>
        </PSAs>
        <InputGranule>
            <InputPointer>MYD03.A2021001.0540.006.2021001222727.hdf</InputPointer>
            <InputPointer>MYD021KM.A2021001.0540.006.2021001223406.hdf</InputPointer>
            <InputPointer>MYD35_L2.A2021001.0540.006.2021001223614.hdf</InputPointer>
            <InputPointer>MYD10_L2.A2021001.0540.006.2021001224328.hdf</InputPointer>
            <InputPointer>MYD07_L2.A2021001.0540.006.2021001223641.hdf</InputPointer>
            <InputPointer>MYD03.A2021001.0715.006.2021001223128.hdf</InputPointer>
            <InputPointer>MYD021KM.A2021001.0715.006.2021001223647.hdf</InputPointer>
            <InputPointer>MYD35_L2.A2021001.0715.006.2021001223843.hdf</InputPointer>
            <InputPointer>MYD10_L2.A2021001.0715.006.2021001224627.hdf</InputPointer>
            <InputPointer>MYD07_L2.A2021001.0715.006.2021001223909.hdf</InputPointer>
            <InputPointer>MYD03.A2021001.1925.006.2021002162014.hdf</InputPointer>
            <InputPointer>MYD021KM.A2021001.1925.006.2021002162311.hdf</InputPointer>
            <InputPointer>MYD35_L2.A2021001.1925.006.2021002162353.hdf</InputPointer>
            <InputPointer>MYD07_L2.A2021001.1925.006.2021002162413.hdf</InputPointer>
            <InputPointer>MYD03.A2021001.1930.006.2021002162028.hdf</InputPointer>
            <InputPointer>MYD021KM.A2021001.1930.006.2021002162257.hdf</InputPointer>
            <InputPointer>MYD35_L2.A2021001.1930.006.2021002162339.hdf</InputPointer>
            <InputPointer>MYD07_L2.A2021001.1930.006.2021002162357.hdf</InputPointer>
        </InputGranule>
        <BrowseProduct>
            <BrowseGranuleId>UR:10:DsShESDTUR:UR:15:DsShSciServerUR:13:[EDC:DSSDSRV]:24:BR:Browse.001:2428328555</BrowseGranuleId>
        </BrowseProduct>
    </GranuleURMetaData>
</GranuleMetaDataFile>


